README.md
setup.cfg
setup.py
di_di_napalm_ros/__init__.py
di_di_napalm_ros/query.py
di_di_napalm_ros/ros.py
di_di_napalm_ros/utils.py
di_di_napalm_ros.egg-info/PKG-INFO
di_di_napalm_ros.egg-info/SOURCES.txt
di_di_napalm_ros.egg-info/dependency_links.txt
di_di_napalm_ros.egg-info/requires.txt
di_di_napalm_ros.egg-info/top_level.txt