Metadata-Version: 2.1
Name: di-di-napalm-ros
Version: 0.1
Summary: functionality for mikrotik devices, via netmiko connection for netbox
Home-page: UNKNOWN
Author: Ilya Gulin
License: Apache 2.0
Platform: UNKNOWN
